{"page_id": 1019094, "slug": "forum_rebuild-discussion_19094", "title": "New Unit 02", "display_title": "New Unit 02", "namespace": 0, "content_model": "forum", "language": "en", "wikitext": "[]: &quot;New Unit 02&quot; &nbsp;&nbsp;&nbsp;&nbsp;&nbsp; &nbsp;&nbsp;&nbsp;&nbsp;&nbsp; Quote Post by Joseki &raquo; Sat Aug 05, 2017 7:11 pm From Minna no Eva fan. 新2号機 = New Unit 2 The design looks very Yamashita with many details and it generally looks more menacing than usual. It's a very good looking Eva. I'm not sure if it is slightly pink or is just the way it's colored but I really dig the design anyway. EDIT - From the Evangelion:3.0+1.0 teaser 2\n\n[]: Re: First official image of &quot;Unit 08+02&quot;/&quot;New unit 02&quot; &nbsp;&nbsp;&nbsp;&nbsp;&nbsp; &nbsp;&nbsp;&nbsp;&nbsp;&nbsp; Quote Post by Ray &raquo; Sat Aug 05, 2017 8:20 pm We went from an Eva that looked like two evas stiched together vertically. To an eva with a head that looks like two heads were chopped vertically and put one on top of the other.\n\n[]: Re: First official image of &quot;Unit 08+02&quot;/&quot;New unit 02&quot; &nbsp;&nbsp;&nbsp;&nbsp;&nbsp; &nbsp;&nbsp;&nbsp;&nbsp;&nbsp; Quote Post by Settie &raquo; Sat Aug 05, 2017 8:26 pm I don't know if it's the artist style but that reminds me way more of a fusion of Unit-2 and Unit-3 than 02+08.\n\n[]: Re: First official image of &quot;Unit 08+02&quot;/&quot;New unit 02&quot; &nbsp;&nbsp;&nbsp;&nbsp;&nbsp; &nbsp;&nbsp;&nbsp;&nbsp;&nbsp; Quote Post by BlueBasilisk &raquo; Sat Aug 05, 2017 8:31 pm The only thing that really invokes Unit 08 there is the ear thingy between the eyes and the spiked on the back of the jaw. Might be an entirely new build for Unit 02!\n\n[]: Re: First official image of &quot;Unit 08+02&quot;/&quot;New unit 02&quot; &nbsp;&nbsp;&nbsp;&nbsp;&nbsp; &nbsp;&nbsp;&nbsp;&nbsp;&nbsp; Quote Post by Gendo'sPapa &raquo; Sat Aug 05, 2017 8:51 pm Solid! People flipped out about the very cheap looking Two-Face Evangelion from the teaser at the end of 3.0 but I could always tell that was just a temp model for the teaser. Should be an interesting Evangelion in the film. Possibly a dual piloted Unit with Asuka &amp; Mari.\n\n[]: Re: First official image of &quot;Unit 08+02&quot;/&quot;New unit 02&quot; &nbsp;&nbsp;&nbsp;&nbsp;&nbsp; &nbsp;&nbsp;&nbsp;&nbsp;&nbsp; Quote Post by FreakyFilmFan4ever &raquo; Sat Aug 05, 2017 8:56 pm Best thing I've seen from Japan all year.\n\n[]: Re: First official image of &quot;Unit 08+02&quot;/&quot;New unit 02&quot; &nbsp;&nbsp;&nbsp;&nbsp;&nbsp; &nbsp;&nbsp;&nbsp;&nbsp;&nbsp; Quote Post by BlueBasilisk &raquo; Sat Aug 05, 2017 9:17 pm I can't shake the feeling I've seen something similar to this design before. One of the Anima versions of Unit 02, maybe?\n\n[]: Re: First official image of &quot;Unit 08+02&quot;/&quot;New unit 02&quot; &nbsp;&nbsp;&nbsp;&nbsp;&nbsp; &nbsp;&nbsp;&nbsp;&nbsp;&nbsp; Quote Post by Sailor Star Dust &raquo; Sat Aug 05, 2017 11:18 pm The look feels extremely familiar to me, too, but I just can't place it. Either way, if this is the &quot;merged&quot; Eva 08+02, I love it. Great stuff all around!\n\n[]: Re: First official image of &quot;Unit 08+02&quot;/&quot;New unit 02&quot; &nbsp;&nbsp;&nbsp;&nbsp;&nbsp; &nbsp;&nbsp;&nbsp;&nbsp;&nbsp; Quote Post by The Cruel &raquo; Sat Aug 05, 2017 11:44 pm The day of Vengeance and Truth comes closer with every news we get to 3.0+1.0. The valkyrie and the force of nature must strengthen their bond to unleash carnage and horror on their mortal foes with Eva 8+2. The design of the Eva has the typical characteristics of their former evas and I do think it has the matching color paterns.\n\n[]: Re: First official image of &quot;Unit 08+02&quot;/&quot;New unit 02&quot; &nbsp;&nbsp;&nbsp;&nbsp;&nbsp; &nbsp;&nbsp;&nbsp;&nbsp;&nbsp; Quote Post by robersora &raquo; Sun Aug 06, 2017 12:38 am I hoped for a reveal of the English title, but this design is so awesome, I can't complain.\n\n[]: Re: First official image of &quot;Unit 08+02&quot;/&quot;New unit 02&quot; &nbsp;&nbsp;&nbsp;&nbsp;&nbsp; &nbsp;&nbsp;&nbsp;&nbsp;&nbsp; Quote Post by BlueBasilisk &raquo; Sun Aug 06, 2017 12:52 am Sailor Star Dust wrote: The look feels extremely familiar to me, too, but I just can't place it. Either way, if this is the &quot;merged&quot; Eva 08+02, I love it. Great stuff all around!\n\n[]: Re: First official image of &quot;New Unit 2&quot; &nbsp;&nbsp;&nbsp;&nbsp;&nbsp; &nbsp;&nbsp;&nbsp;&nbsp;&nbsp; Quote Post by Joseki &raquo; Sun Aug 06, 2017 2:03 am So the Eva is called &quot;新2号機&quot; probably, in english &quot;New Unit 2&quot; acording to Google Translate. Apparently the first kanji (新) is &quot;shin&quot;, so the movie is called &quot;Shin Evangelion&quot; and there is a &quot;Shin Evangelion&quot; in it.\n\n[]: Re: First official image of &quot;New Unit 2&quot; &nbsp;&nbsp;&nbsp;&nbsp;&nbsp; &nbsp;&nbsp;&nbsp;&nbsp;&nbsp; Quote Post by Guy Nacks &raquo; Sun Aug 06, 2017 2:43 am This is the second time Anno has drawn a revamped version of Unit 02 for the lantern festival. The first was back in 2011, a little over a year before 3.0 would be released. I think we're on track for a Fall 2018 release.\n\n[]: Re: First official image of &quot;New Unit 2&quot; &nbsp;&nbsp;&nbsp;&nbsp;&nbsp; &nbsp;&nbsp;&nbsp;&nbsp;&nbsp; Quote Post by Sachi &raquo; Sun Aug 06, 2017 2:46 am I feel that much closer to the man and the myth, Anno, knowing that we share a love for best girl and her Eva. Unit 02 has been my long time favorite, and I love seeing it revamped over and over.\n\n[]: Re: First official image of &quot;New Unit 2&quot; &nbsp;&nbsp;&nbsp;&nbsp;&nbsp; &nbsp;&nbsp;&nbsp;&nbsp;&nbsp; Quote Post by Joseki &raquo; Sun Aug 06, 2017 5:55 am I manually checked the colors with Photoshop and it appears to be full pink, there were some spots in the shadows that seemed red but they were just more intense pink. SPOILER: Show\n\n[]: Re: First official image of &quot;New Unit 2&quot; &nbsp;&nbsp;&nbsp;&nbsp;&nbsp; &nbsp;&nbsp;&nbsp;&nbsp;&nbsp; Quote Post by FreakyFilmFan4ever &raquo; Sun Aug 06, 2017 5:56 am Could just be Anno's muted color style when it comes to these festivals. The previous years' illustrations were equally as muted and minimalistic.\n\n[]: Re: First official image of &quot;New Unit 2&quot; &nbsp;&nbsp;&nbsp;&nbsp;&nbsp; &nbsp;&nbsp;&nbsp;&nbsp;&nbsp; Quote Post by Joseki &raquo; Sun Aug 06, 2017 6:06 am Unit 02 seemed more red to me back in 2011: SPOILER: Show\n\n[]: Re: First official image of &quot;New Unit 2&quot; &nbsp;&nbsp;&nbsp;&nbsp;&nbsp; &nbsp;&nbsp;&nbsp;&nbsp;&nbsp; Quote Post by ElMariachi &raquo; Sun Aug 06, 2017 5:25 pm Well, that new &quot;Super&quot; Eva 02 could indicate that there will be at least a minor time skip during Shin Eva, as I doubt that regrowing most of an Eva and refurbishing it with new armor can be done in a couple of days.\n\n[]: Re: First official image of &quot;New Unit 2&quot; &nbsp;&nbsp;&nbsp;&nbsp;&nbsp; &nbsp;&nbsp;&nbsp;&nbsp;&nbsp; Quote Post by Ray &raquo; Sun Aug 06, 2017 5:30 pm ElMariachi wrote: Well, that new &quot;Super&quot; Eva 02 could indicate that there will be at least a minor time skip during Shin Eva, as I doubt that regrowing most of an Eva and refurbishing it with new armor can be done in a couple of days.\n\n[]: Re: First official image of &quot;New Unit 2&quot; &nbsp;&nbsp;&nbsp;&nbsp;&nbsp; &nbsp;&nbsp;&nbsp;&nbsp;&nbsp; Quote Post by TMBounty_Hunter &raquo; Mon Aug 07, 2017 2:02 pm I'm lovin' it.® Now where's my god damn model kit of it?", "html": "", "summary": "[]: &quot;New Unit 02&quot; &nbsp;&nbsp;&nbsp;&nbsp;&nbsp; &nbsp;&nbsp;&nbsp;&nbsp;&nbsp; Quote Post by Joseki &raquo; Sat Aug 05, 2017 7:11 pm From Minna no Eva fan. 新2号機 = New Unit 2 The design looks very Yamashita with many details and it generally looks more menacing than usual. It's a very good looking Eva. I'm not sure if it is slightly pink or is just the way it's colored but I really dig the design anyway. EDIT - From the Evangelion:3.0+1.0 teaser 2\n\n[]: Re: First official image of &quot", "sections": [], "categories": ["Forum: rebuild-discussion"], "infobox": {}, "templates": [], "internal_links": [], "external_links": [], "iw_links": [], "lang_links": [], "properties": {}, "protection": [], "rev_id": null, "length_bytes": 7323, "parse_warnings": [], "touched_at": null, "references": [], "source_type": "forum", "source_url": "https://forum.evageeks.org/thread/19094/New-Unit-02/", "chunks": [{"article_slug": "forum_rebuild-discussion_19094", "section": "_intro", "content": "Article: New Unit 02\n[]: \"New Unit 02\"             Quote Post by Joseki » Sat Aug 05, 2017 7:11 pm From Minna no Eva fan. 新2号機 = New Unit 2 The design looks very Yamashita with many details and it generally looks more menacing than usual. It's a very good looking Eva. I'm not sure if it is slightly pink or is just the way it's colored but I really dig the design anyway. EDIT - From the Evangelion:3.0+1.0 teaser 2\n\n[]: Re: First official image of \"Unit 08+02\"/\"New unit 02\"             Quote Post by Ray » Sat Aug 05, 2017 8:20 pm We went from an Eva that looked like two evas stiched together vertically. To an eva with a head that looks like two heads were chopped vertically and put one on top of the other.\n\n[]: Re: First official image of \"Unit 08+02\"/\"New unit 02\"             Quote Post by Settie » Sat Aug 05, 2017 8:26 pm I don't know if it's the artist style but that reminds me way more of a fusion of Unit-2 and Unit-3 than 02+08.\n\n[]: Re: First official image of \"Unit 08+02\"/\"New unit 02\"             Quote Post by BlueBasilisk » Sat Aug 05, 2017 8:31 pm The only thing that really invokes Unit 08 there is the ear thingy between the eyes and the spiked on the back of the jaw. Might be an entirely new build for Unit 02!\n\n[]: Re: First official image of \"Unit 08+02\"/\"New unit 02\"             Quote Post by Gendo'sPapa » Sat Aug 05, 2017 8:51 pm Solid! People flipped out about the very cheap looking Two-Face Evangelion from the teaser at the end of 3.0 but I could always tell that was just a temp model for the teaser. Should be an interesting Evangelion in the film. Possibly a dual piloted Unit with Asuka & Mari.\n\n[]: Re: First official image of \"Unit 08+02\"/\"New unit 02\"             Quote Post by FreakyFilmFan4ever » Sat Aug", "position": 0, "token_count": 519}, {"article_slug": "forum_rebuild-discussion_19094", "section": "_intro", "content": "Article: New Unit 02\n. Possibly a dual piloted Unit with Asuka & Mari.\n\n[]: Re: First official image of \"Unit 08+02\"/\"New unit 02\"             Quote Post by FreakyFilmFan4ever » Sat Aug 05, 2017 8:56 pm Best thing I've seen from Japan all year.\n\n[]: Re: First official image of \"Unit 08+02\"/\"New unit 02\"             Quote Post by BlueBasilisk » Sat Aug 05, 2017 9:17 pm I can't shake the feeling I've seen something similar to this design before. One of the Anima versions of Unit 02, maybe?\n\n[]: Re: First official image of \"Unit 08+02\"/\"New unit 02\"             Quote Post by Sailor Star Dust » Sat Aug 05, 2017 11:18 pm The look feels extremely familiar to me, too, but I just can't place it. Either way, if this is the \"merged\" Eva 08+02, I love it. Great stuff all around!\n\n[]: Re: First official image of \"Unit 08+02\"/\"New unit 02\"             Quote Post by The Cruel » Sat Aug 05, 2017 11:44 pm The day of Vengeance and Truth comes closer with every news we get to 3.0+1.0. The valkyrie and the force of nature must strengthen their bond to unleash carnage and horror on their mortal foes with Eva 8+2. The design of the Eva has the typical characteristics of their former evas and I do think it has the matching color paterns.\n\n[]: Re: First official image of \"Unit 08+02\"/\"New unit 02\"             Quote Post by robersora » Sun Aug 06, 2017 12:38 am I hoped for a reveal of the English title, but this design is so awesome, I can't complain.\n\n[]: Re: First official image of \"Unit 08+02\"/\"New unit 02\"             Quote Post by BlueBasilisk » Sun Aug 06, 2017 12:52 am Sailor Star Dust wrote: The look feels extremely familiar to me, too, but I just can't place it. Either way, if this is the \"merged\" Eva 08+02,", "position": 1, "token_count": 519}, {"article_slug": "forum_rebuild-discussion_19094", "section": "_intro", "content": "Article: New Unit 02\n 06, 2017 12:52 am Sailor Star Dust wrote: The look feels extremely familiar to me, too, but I just can't place it. Either way, if this is the \"merged\" Eva 08+02, I love it. Great stuff all around!\n\n[]: Re: First official image of \"New Unit 2\"             Quote Post by Joseki » Sun Aug 06, 2017 2:03 am So the Eva is called \"新2号機\" probably, in english \"New Unit 2\" acording to Google Translate. Apparently the first kanji (新) is \"shin\", so the movie is called \"Shin Evangelion\" and there is a \"Shin Evangelion\" in it.\n\n[]: Re: First official image of \"New Unit 2\"             Quote Post by Guy Nacks » Sun Aug 06, 2017 2:43 am This is the second time Anno has drawn a revamped version of Unit 02 for the lantern festival. The first was back in 2011, a little over a year before 3.0 would be released. I think we're on track for a Fall 2018 release.\n\n[]: Re: First official image of \"New Unit 2\"             Quote Post by Sachi » Sun Aug 06, 2017 2:46 am I feel that much closer to the man and the myth, Anno, knowing that we share a love for best girl and her Eva. Unit 02 has been my long time favorite, and I love seeing it revamped over and over.\n\n[]: Re: First official image of \"New Unit 2\"             Quote Post by Joseki » Sun Aug 06, 2017 5:55 am I manually checked the colors with Photoshop and it appears to be full pink, there were some spots in the shadows that seemed red but they were just more intense pink. SPOILER: Show\n\n[]: Re: First official image of \"New Unit 2\"             Quote Post by FreakyFilmFan4ever » Sun Aug 06, 2017 5:56 am Could just be Anno's muted color style when it comes to these festivals. The previous years' illustrations were equally as muted and minimalistic.\n\n[]: Re: First official image of \"New Unit 2\"             Quote Post by Joseki", "position": 2, "token_count": 519}, {"article_slug": "forum_rebuild-discussion_19094", "section": "_intro", "content": "Article: New Unit 02\n be Anno's muted color style when it comes to these festivals. The previous years' illustrations were equally as muted and minimalistic.\n\n[]: Re: First official image of \"New Unit 2\"             Quote Post by Joseki » Sun Aug 06, 2017 6:06 am Unit 02 seemed more red to me back in 2011: SPOILER: Show\n\n[]: Re: First official image of \"New Unit 2\"             Quote Post by ElMariachi » Sun Aug 06, 2017 5:25 pm Well, that new \"Super\" Eva 02 could indicate that there will be at least a minor time skip during Shin Eva, as I doubt that regrowing most of an Eva and refurbishing it with new armor can be done in a couple of days.\n\n[]: Re: First official image of \"New Unit 2\"             Quote Post by Ray » Sun Aug 06, 2017 5:30 pm ElMariachi wrote: Well, that new \"Super\" Eva 02 could indicate that there will be at least a minor time skip during Shin Eva, as I doubt that regrowing most of an Eva and refurbishing it with new armor can be done in a couple of days.\n\n[]: Re: First official image of \"New Unit 2\"             Quote Post by TMBounty_Hunter » Mon Aug 07, 2017 2:02 pm I'm lovin' it.® Now where's my god damn model kit of it?", "position": 3, "token_count": 333}]}